soli/__init__.py
soli/config.py
soli/graph.py
soli/logger.py
soli/models.py
soli_python-0.1.5.dist-info/LICENSE
soli_python-0.1.5.dist-info/METADATA
soli_python-0.1.5.dist-info/WHEEL
soli_python-0.1.5.dist-info/RECORD
