Metadata-Version: 2.1
Name: soli-python
Version: 0.1.5
Summary: Python library for SOLI, the Standard for Open Legal Information
Home-page: https://openlegalstandard.org/
License: MIT
Keywords: legal,information,standard,soli,open
Author: ALEA Institute
Author-email: hello@aleainstitute.ai
Requires-Python: >=3.10,<4.0.0
Classifier: Development Status :: 3 - Alpha
Classifier: Intended Audience :: Developers
Classifier: Intended Audience :: Legal Industry
Classifier: Intended Audience :: Science/Research
Classifier: License :: OSI Approved :: MIT License
Classifier: Operating System :: OS Independent
Classifier: Programming Language :: Python
Classifier: Programming Language :: Python :: 3
Classifier: Programming Language :: Python :: 3.10
Classifier: Programming Language :: Python :: 3.11
Classifier: Programming Language :: Python :: 3.12
Classifier: Topic :: Scientific/Engineering :: Artificial Intelligence
Classifier: Topic :: Scientific/Engineering :: Information Analysis
Classifier: Topic :: Software Development :: Libraries :: Python Modules
Classifier: Topic :: Text Processing :: Markup :: XML
Classifier: Topic :: Utilities
Provides-Extra: search
Requires-Dist: alea-llm-client (>=0.1.1,<0.2.0) ; extra == "search"
Requires-Dist: httpx (>=0.27.2,<0.28.0)
Requires-Dist: lxml (>=5.2.2,<6.0.0)
Requires-Dist: marisa-trie (>=1.2.0,<2.0.0) ; extra == "search"
Requires-Dist: pydantic (>=2.8.2,<3.0.0)
Requires-Dist: rapidfuzz (>=3.10.0,<4.0.0) ; extra == "search"
Project-URL: Documentation, https://openlegalstandard.org/docs/
Project-URL: Repository, https://github.com/alea-institute/soli-python
